assesment_creator/__init__.py
assesment_creator/cutom_exception.py
assesment_creator/get_assesment.py
assesment_creator/helper.py
assesment_creator/logger.py
assesment_creator-0.0.6.dist-info/LICENSE
assesment_creator-0.0.6.dist-info/METADATA
assesment_creator-0.0.6.dist-info/WHEEL
assesment_creator-0.0.6.dist-info/top_level.txt
assesment_creator-0.0.6.dist-info/RECORD
